Workbook

Sheet Base Total
B2: Cliente | C2: Segmento | D2: Estado | E2: Mês_Ano | F2: R$ Receita | G2: R$ Custo | H2: Status | I2: Margem Bruta Mês | J2: Clientes Margem Bruta
B3: A | C3: =VLOOKUP(B3,Tabela4[],2,FALSE()) -> Média | D3: =VLOOKUP(B3,Tabela4[],3,FALSE()) -> Rio de Janeiro | E3: 2024-12 | F3: =VLOOKUP($K3,'FATURAMENTO '!$A$2:$E$302,4,FALSE()) -> 21231 | G3: =VLOOKUP($K3,'FATURAMENTO '!$A$2:$E$302,5,FALSE()) -> 13598.65 | H3: =VLOOKUP($K3,CHURN!$A$2:$E$302,4,FALSE()) -> Cancelado | I3: =(F3-G3)/F3 -> 0.35949084 | J3: =IF(INDEX($I$3:$I$302,MATCH(B3,$B$3:$B$302,0))>50%,"Alto valor",IF(INDEX($I$3:$I$302,MATCH(B3,$B$3:$B$302,0))>=30%,"Médio valor","Baixo valor")) -> Médio valor | K3: =CONCATENATE(B3,E3) -> A2024-12
B4: A | C4: =VLOOKUP(B4,Tabela4[],2,FALSE()) -> Média | D4: =VLOOKUP(B4,Tabela4[],3,FALSE()) -> Rio de Janeiro | E4: 2025-01 | F4: =VLOOKUP($K4,'FATURAMENTO '!$A$2:$E$302,4,FALSE()) -> 35273 | G4: =VLOOKUP($K4,'FATURAMENTO '!$A$2:$E$302,5,FALSE()) -> 24414.45 | H4: =VLOOKUP($K4,CHURN!$A$2:$E$302,4,FALSE()) -> Ativo | I4: =(F4-G4)/F4 -> 0.30784311 | J4: =IF(INDEX($I$3:$I$302,MATCH(B4,$B$3:$B$302,0))>50%,"Alto valor",IF(INDEX($I$3:$I$302,MATCH(B4,$B$3:$B$302,0))>=30%,"Médio valor","Baixo valor")) -> Médio valor | K4: =CONCATENATE(B4,E4) -> A2025-01
B5: A | C5: =VLOOKUP(B5,Tabela4[],2,FALSE()) -> Média | D5: =VLOOKUP(B5,Tabela4[],3,FALSE()) -> Rio de Janeiro | E5: 2025-02 | F5: =VLOOKUP($K5,'FATURAMENTO '!$A$2:$E$302,4,FALSE()) -> 12897 | G5: =VLOOKUP($K5,'FATURAMENTO '!$A$2:$E$302,5,FALSE()) -> 7662.32 | H5: =VLOOKUP($K5,CHURN!$A$2:$E$302,4,FALSE()) -> Ativo | I5: =(F5-G5)/F5 -> 0.40588354 | J5: =IF(INDEX($I$3:$I$302,MATCH(B5,$B$3:$B$302,0))>50%,"Alto valor",IF(INDEX($I$3:$I$302,MATCH(B5,$B$3:$B$302,0))>=30%,"Médio valor","Baixo valor")) -> Médio valor | K5: =CONCATENATE(B5,E5) -> A2025-02
B6: A | C6: =VLOOKUP(B6,Tabela4[],2,FALSE()) -> Média | D6: =VLOOKUP(B6,Tabela4[],3,FALSE()) -> Rio de Janeiro | E6: 2025-03 | F6: =VLOOKUP($K6,'FATURAMENTO '!$A$2:$E$302,4,FALSE()) -> 29303 | G6: =VLOOKUP($K6,'FATURAMENTO '!$A$2:$E$302,5,FALSE()) -> 16188.04 | H6: =VLOOKUP($K6,CHURN!$A$2:$E$302,4,FALSE()) -> Ativo | I6: =(F6-G6)/F6 -> 0.44756373 | J6: =IF(INDEX($I$3:$I$302,MATCH(B6,$B$3:$B$302,0))>50%,"Alto valor",IF(INDEX($I$3:$I$302,MATCH(B6,$B$3:$B$302,0))>=30%,"Médio valor","Baixo valor")) -> Médio valor | K6: =CONCATENATE(B6,E6) -> A2025-03
B7: A | C7: =VLOOKUP(B7,Tabela4[],2,FALSE()) -> Média | D7: =VLOOKUP(B7,Tabela4[],3,FALSE()) -> Rio de Janeiro | E7: 2025-04 | F7: =VLOOKUP($K7,'FATURAMENTO '!$A$2:$E$302,4,FALSE()) -> 42192 | G7: =VLOOKUP($K7,'FATURAMENTO '!$A$2:$E$302,5,FALSE()) -> 26160.68 | H7: =VLOOKUP($K7,CHURN!$A$2:$E$302,4,FALSE()) -> Ativo | I7: =(F7-G7)/F7 -> 0.37996113 | J7: =IF(INDEX($I$3:$I$302,MATCH(B7,$B$3:$B$302,0))>50%,"Alto valor",IF(INDEX($I$3:$I$302,MATCH(B7,$B$3:$B$302,0))>=30%,"Médio valor","Baixo valor")) -> Médio valor | K7: =CONCATENATE(B7,E7) -> A2025-04
B8: A | C8: =VLOOKUP(B8,Tabela4[],2,FALSE()) -> Média | D8: =VLOOKUP(B8,Tabela4[],3,FALSE()) -> Rio de Janeiro | E8: 2025-05 | F8: =VLOOKUP($K8,'FATURAMENTO '!$A$2:$E$302,4,FALSE()) -> 13155 | G8: =VLOOKUP($K8,'FATURAMENTO '!$A$2:$E$302,5,FALSE()) -> 7317.15 | H8: =VLOOKUP($K8,CHURN!$A$2:$E$302,4,FALSE()) -> Ativo | I8: =(F8-G8)/F8 -> 0.44377423 | J8: =IF(INDEX($I$3:$I$302,MATCH(B8,$B$3:$B$302,0))>50%,"Alto valor",IF(INDEX($I$3:$I$302,MATCH(B8,$B$3:$B$302,0))>=30%,"Médio valor","Baixo valor")) -> Médio valor | K8: =CONCATENATE(B8,E8) -> A2025-05
B9: B | C9: =VLOOKUP(B9,Tabela4[],2,FALSE()) -> Média | D9: =VLOOKUP(B9,Tabela4[],3,FALSE()) -> Distrito Federal | E9: 2024-12 | F9: =VLOOKUP($K9,'FATURAMENTO '!$A$2:$E$302,4,FALSE()) -> 39211 | G9: =VLOOKUP($K9,'FATURAMENTO '!$A$2:$E$302,5,FALSE()) -> 25382.97 | H9: =VLOOKUP($K9,CHURN!$A$2:$E$302,4,FALSE()) -> Ativo | I9: =(F9-G9)/F9 -> 0.35265691 | J9: =IF(INDEX($I$3:$I$302,MATCH(B9,$B$3:$B$302,0))>50%,"Alto valor",IF(INDEX($I$3:$I$302,MATCH(B9,$B$3:$B$302,0))>=30%,"Médio valor","Baixo valor")) -> Médio valor | K9: =CONCATENATE(B9,E9) -> B2024-12
B10: B | C10: =VLOOKUP(B10,Tabela4[],2,FALSE()) -> Média | D10: =VLOOKUP(B10,Tabela4[],3,FALSE()) -> Distrito Federal | E10: 2025-01 | F10: =VLOOKUP($K10,'FATURAMENTO '!$A$2:$E$302,4,FALSE()) -> 26027 | G10: =VLOOKUP($K10,'FATURAMENTO '!$A$2:$E$302,5,FALSE()) -> 19476.55 | H10: =VLOOKUP($K10,CHURN!$A$2:$E$302,4,FALSE()) -> Ativo | I10: =(F10-G10)/F10 -> 0.25167903 | J10: =IF(INDEX($I$3:$I$302,MATCH(B10,$B$3:$B$302,0))>50%,"Alto valor",IF(INDEX($I$3:$I$302,MATCH(B10,$B$3:$B$302,0))>=30%,"Médio valor","Baixo valor")) -> Médio valor | K10: =CONCATENATE(B10,E10) -> B2025-01
B11: B | C11: =VLOOKUP(B11,Tabela4[],2,FALSE()) -> Média | D11: =VLOOKUP(B11,Tabela4[],3,FALSE()) -> Distrito Federal | E11: 2025-02 | F11: =VLOOKUP($K11,'FATURAMENTO '!$A$2:$E$302,4,FALSE()) -> 35119 | G11: =VLOOKUP($K11,'FATURAMENTO '!$A$2:$E$302,5,FALSE()) -> 20804.3 | H11: =VLOOKUP($K11,CHURN!$A$2:$E$302,4,FALSE()) -> Ativo | I11: =(F11-G11)/F11 -> 0.40760557 | J11: =IF(INDEX($I$3:$I$302,MATCH(B11,$B$3:$B$302,0))>50%,"Alto valor",IF(INDEX($I$3:$I$302,MATCH(B11,$B$3:$B$302,0))>=30%,"Médio valor","Baixo valor")) -> Médio valor | K11: =CONCATENATE(B11,E11) -> B2025-02
B12: B | C12: =VLOOKUP(B12,Tabela4[],2,FALSE()) -> Média | D12: =VLOOKUP(B12,Tabela4[],3,FALSE()) -> Distrito Federal | E12: 2025-03 | F12: =VLOOKUP($K12,'FATURAMENTO '!$A$2:$E$302,4,FALSE()) -> 21363 | G12: =VLOOKUP($K12,'FATURAMENTO '!$A$2:$E$302,5,FALSE()) -> 16304.52 | H12: =VLOOKUP($K12,CHURN!$A$2:$E$302,4,FALSE()) -> Ativo | I12: =(F12-G12)/F12 -> 0.23678697 | J12: =IF(INDEX($I$3:$I$302,MATCH(B12,$B$3:$B$302,0))>50%,"Alto valor",IF(INDEX($I$3:$I$302,MATCH(B12,$B$3:$B$302,0))>=30%,"Médio valor","Baixo valor")) -> Médio valor | K12: =CONCATENATE(B12,E12) -> B2025-03
B13: B | C13: =VLOOKUP(B13,Tabela4[],2,FALSE()) -> Média | D13: =VLOOKUP(B13,Tabela4[],3,FALSE()) -> Distrito Federal | E13: 2025-04 | F13: =VLOOKUP($K13,'FATURAMENTO '!$A$2:$E$302,4,FALSE()) -> 7179 | G13: =VLOOKUP($K13,'FATURAMENTO '!$A$2:$E$302,5,FALSE()) -> 4489.85 | H13: =VLOOKUP($K13,CHURN!$A$2:$E$302,4,FALSE()) -> Cancelado | I13: =(F13-G13)/F13 -> 0.3745856 | J13: =IF(INDEX($I$3:$I$302,MATCH(B13,$B$3:$B$302,0))>50%,"Alto valor",IF(INDEX($I$3:$I$302,MATCH(B13,$B$3:$B$302,0))>=30%,"Médio valor","Baixo valor")) -> Médio valor | K13: =CONCATENATE(B13,E13) -> B2025-04
B14: B | C14: =VLOOKUP(B14,Tabela4[],2,FALSE()) -> Média | D14: =VLOOKUP(B14,Tabela4[],3,FALSE()) -> Distrito Federal | E14: 2025-05 | F14: =VLOOKUP($K14,'FATURAMENTO '!$A$2:$E$302,4,FALSE()) -> 26815 | G14: =VLOOKUP($K14,'FATURAMENTO '!$A$2:$E$302,5,FALSE()) -> 14788.29 | H14: =VLOOKUP($K14,CHURN!$A$2:$E$302,4,FALSE()) -> Ativo | I14: =(F14-G14)/F14 -> 0.44850681 | J14: =IF(INDEX($I$3:$I$302,MATCH(B14,$B$3:$B$302,0))>50%,"Alto valor",IF(INDEX($I$3:$I$302,MATCH(B14,$B$3:$B$302,0))>=30%,"Médio valor","Baixo valor")) -> Médio valor | K14: =CONCATENATE(B14,E14) -> B2025-05
... B302: AW | C302: =VLOOKUP(B302,Tabela4[],2,FALSE()) -> Média | D302: =VLOOKUP(B302,Tabela4[],3,FALSE()) -> Pernambuco | E302: 2025-05 | F302: =VLOOKUP($K302,'FATURAMENTO '!$A$2:$E$302,4,FALSE()) -> 46600 | G302: =VLOOKUP($K302,'FATURAMENTO '!$A$2:$E$302,5,FALSE()) -> 36548.82 | H302: =VLOOKUP($K302,CHURN!$A$2:$E$302,4,FALSE()) -> Ativo | I302: =(F302-G302)/F302 -> 0.21569056 | J302: =IF(INDEX($I$3:$I$302,MATCH(B302,$B$3:$B$302,0))>50%,"Alto valor",IF(INDEX($I$3:$I$302,MATCH(B302,$B$3:$B$302,0))>=30%,"Médio valor","Baixo valor")) -> Médio valor | K302: =CONCATENATE(B302,E302) -> AW2025-05

Sheet CLIENTES
A2: Cliente_id | B2: Segmento | C2: Estado
A3: A | B3: Média | C3: Rio de Janeiro
A4: B | B4: Média | C4: Distrito Federal
A5: C | B5: Grande | C5: São Paulo
A6: D | B6: Pequena | C6: Rio de Janeiro
A7: E | B7: Média | C7: São Paulo
A8: F | B8: Grande | C8: Ceará
A9: G | B9: Média | C9: Minas Gerais
A10: H | B10: Grande | C10: Pernambuco
A11: I | B11: Média | C11: Minas Gerais
A12: J | B12: Grande | C12: Bahia
A13: K | B13: Pequena | C13: Santa Catarina
... A52: AW | B52: Média | C52: Pernambuco

Sheet FATURAMENTO 
A2: Concatenar | B2: cliente_id | C2: mes_ano | D2: R$ Receita | E2: R$ Custo
A3: =CONCATENATE(Tabela13[[#This Row],[cliente_id]],Tabela13[[#This Row],[mes_ano]]) -> A2024-12 | B3: A | C3: 2024-12 | D3: 21231 | E3: 13598.65
A4: =CONCATENATE(Tabela13[[#This Row],[cliente_id]],Tabela13[[#This Row],[mes_ano]]) -> A2025-01 | B4: A | C4: 2025-01 | D4: 35273 | E4: 24414.45
A5: =CONCATENATE(Tabela13[[#This Row],[cliente_id]],Tabela13[[#This Row],[mes_ano]]) -> A2025-02 | B5: A | C5: 2025-02 | D5: 12897 | E5: 7662.32
A6: =CONCATENATE(Tabela13[[#This Row],[cliente_id]],Tabela13[[#This Row],[mes_ano]]) -> A2025-03 | B6: A | C6: 2025-03 | D6: 29303 | E6: 16188.04
A7: =CONCATENATE(Tabela13[[#This Row],[cliente_id]],Tabela13[[#This Row],[mes_ano]]) -> A2025-04 | B7: A | C7: 2025-04 | D7: 42192 | E7: 26160.68
A8: =CONCATENATE(Tabela13[[#This Row],[cliente_id]],Tabela13[[#This Row],[mes_ano]]) -> A2025-05 | B8: A | C8: 2025-05 | D8: 13155 | E8: 7317.15
A9: =CONCATENATE(Tabela13[[#This Row],[cliente_id]],Tabela13[[#This Row],[mes_ano]]) -> B2024-12 | B9: B | C9: 2024-12 | D9: 39211 | E9: 25382.97
A10: =CONCATENATE(Tabela13[[#This Row],[cliente_id]],Tabela13[[#This Row],[mes_ano]]) -> B2025-01 | B10: B | C10: 2025-01 | D10: 26027 | E10: 19476.55
A11: =CONCATENATE(Tabela13[[#This Row],[cliente_id]],Tabela13[[#This Row],[mes_ano]]) -> B2025-02 | B11: B | C11: 2025-02 | D11: 35119 | E11: 20804.3
A12: =CONCATENATE(Tabela13[[#This Row],[cliente_id]],Tabela13[[#This Row],[mes_ano]]) -> B2025-03 | B12: B | C12: 2025-03 | D12: 21363 | E12: 16304.52
A13: =CONCATENATE(Tabela13[[#This Row],[cliente_id]],Tabela13[[#This Row],[mes_ano]]) -> B2025-04 | B13: B | C13: 2025-04 | D13: 7179 | E13: 4489.85
A14: =CONCATENATE(Tabela13[[#This Row],[cliente_id]],Tabela13[[#This Row],[mes_ano]]) -> B2025-05 | B14: B | C14: 2025-05 | D14: 26815 | E14: 14788.29
... A302: =CONCATENATE(Tabela13[[#This Row],[cliente_id]],Tabela13[[#This Row],[mes_ano]]) -> AW2025-05 | B302: AW | C302: 2025-05 | D302: 46600 | E302: 36548.82

Sheet CHURN
A2: Concatenar | B2: Cliente_id | C2: mês_ano | D2: status | E2: receita
A3: =CONCATENATE(B3,C3) -> A2024-12 | B3: A | C3: 2024-12 | D3: Cancelado | E3: 21231
A4: =CONCATENATE(B4,C4) -> A2025-01 | B4: A | C4: 2025-01 | D4: Ativo | E4: 35273
A5: =CONCATENATE(B5,C5) -> A2025-02 | B5: A | C5: 2025-02 | D5: Ativo | E5: 12897
A6: =CONCATENATE(B6,C6) -> A2025-03 | B6: A | C6: 2025-03 | D6: Ativo | E6: 29303
A7: =CONCATENATE(B7,C7) -> A2025-04 | B7: A | C7: 2025-04 | D7: Ativo | E7: 42192
A8: =CONCATENATE(B8,C8) -> A2025-05 | B8: A | C8: 2025-05 | D8: Ativo | E8: 13155
A9: =CONCATENATE(B9,C9) -> B2024-12 | B9: B | C9: 2024-12 | D9: Ativo | E9: 39211
A10: =CONCATENATE(B10,C10) -> B2025-01 | B10: B | C10: 2025-01 | D10: Ativo | E10: 26027
A11: =CONCATENATE(B11,C11) -> B2025-02 | B11: B | C11: 2025-02 | D11: Ativo | E11: 35119
A12: =CONCATENATE(B12,C12) -> B2025-03 | B12: B | C12: 2025-03 | D12: Ativo | E12: 21363
A13: =CONCATENATE(B13,C13) -> B2025-04 | B13: B | C13: 2025-04 | D13: Cancelado | E13: 7179
A14: =CONCATENATE(B14,C14) -> B2025-05 | B14: B | C14: 2025-05 | D14: Ativo | E14: 26815
... A302: =CONCATENATE(B302,C302) -> AW2025-05 | B302: AW | C302: 2025-05 | D302: Ativo | E302: 46600
